matreshka/__init__.py
matreshka/api.py
matreshka-0.2.3.dist-info/METADATA
matreshka-0.2.3.dist-info/WHEEL
matreshka-0.2.3.dist-info/licenses/LICENSE
matreshka-0.2.3.dist-info/RECORD
