Metadata-Version: 2.1
Name: matreshka
Version: 0.2.3
Summary: The program unpacks *tar.gz archive nested like a doll.
Project-URL: Homepage, https://github.com/SETTER2000/matreshka
Project-URL: Bug Tracker, https://github.com/SETTER2000/matreshka/issues
Author-email: setter <lphp@mail.ru>
License:                     GNU GENERAL PUBLIC LICENSE
License-File: LICENSE
Classifier: License :: OSI Approved :: MIT License
Classifier: Operating System :: OS Independent
Classifier: Programming Language :: Python :: 3
Requires-Python: >=3.9
